RAGFast/RAGFAST.py
RAGFast/__init__.py
RAGFast-0.0.3.dist-info/LICENSE
RAGFast-0.0.3.dist-info/METADATA
RAGFast-0.0.3.dist-info/WHEEL
RAGFast-0.0.3.dist-info/top_level.txt
RAGFast-0.0.3.dist-info/RECORD
